{
  "426951090": {
    "active_tasks": [
      "Поправить лендинг для партнеров."
    ],
    "done_tasks": [],
    "moved_tasks": [],
    "last_summary": "",
    "last_plan_text": "📅 План на день — 16 марта 2026 (понедельник)\n\nПожары:\n- Настроить СМС для завтрашнего вебинара (срочно, чтобы подготовить отправку)\n- Отправить СМС для завтрашнего вебинара (сегодня нужно)\n- Пройтись по чек-листу перед вебинаром (важно, т.к. завтра вебинар)\n\nЧужие срочности:\n- нет отдельных задач, все задачи связаны с вебинаром — это внешние сроки, но все уже в пожарах\n\nЖизнь:\n- нет\n\nУбрать / перенести:\n- нет, все задачи важны и связаны с завтрашним мероприятием\n\nГлавное:\n1. Настроить СМС для завтрашнего вебинара\n2. Отправить СМС для завтрашнего вебинара\n3. Пройтись по чек-листу перед вебинаром\n\nРиск перегруза: низкий (задач немного, но все важные, в пределах одного проекта)\n\nПлан:  \n09:00–09:45 Настроить СМС для завтрашнего вебинара (сделать техническую настройку)  \n09:45–10:00 Буфер / переключение  \n10:00–10:30 Отправить СМС для завтрашнего вебинара (прогнать рассылку)  \n10:30–10:45 Буфер / переключение  \n10:45–11:30 Пройтись по чек-листу перед вебинаром (проверить все пункты, подготовить материалы)  \n11:30–13:00 Резерв / доработка по вебинару, свободное время для вопросов и уточнений  \n13:00–14:00 Обед  \n14:00–18:00 Работа по другим задачам или подготовка к следующему мероприятию (если есть) / отдых / мелкие задачи (в текущем списке нет)",
    "last_plan_type": "day",
    "last_review": "",
    "daily_reviews": [],
    "weekly_reports": [],
    "weekly_plan_text": "",
    "weekly_plan_days": {
      "mon": [
        "Отправить СМС для завтрашнего вебинара",
        "Настроить СМС для завтрашнего вебинара",
        "Пройтись по чек-листу перед вебинаром"
      ],
      "tue": [],
      "wed": [],
      "thu": [],
      "fri": [],
      "sat": [],
      "sun": []
    },
    "weekly_plan_week_key": "",
    "last_day_plan_date": "2026-03-16"
  },
  "_meta": {
    "registered_users": [
      426951090
    ]
  }
}